<databaseChangeLog xmlns="http://www.liquibase.org/xml/ns/dbchangelog"
	xmlns:xsi="http://www.w3.org/2001/XMLSchema-instance"
	xsi:schemaLocation="http://www.liquibase.org/xml/ns/dbchangelog http://www.liquibase.org/xml/ns/dbchangelog/dbchangelog-3.5.xsd">

	<include file="page/0001_create_page.xml" relativeToChangelogFile="true"/>
	<include file="company/0002_create_company.xml" relativeToChangelogFile="true"/>
	<include file="series/0003_create_series.xml" relativeToChangelogFile="true"/>
	<include file="season/0004_create_season.xml" relativeToChangelogFile="true"/>
	<include file="performer/0005_create_performer.xml" relativeToChangelogFile="true"/>
	<include file="staff/0006_create_staff.xml" relativeToChangelogFile="true"/>
	<include file="astronomical_object/0007_create_astronomical_object.xml" relativeToChangelogFile="true"/>
	<include file="character/0008_create_character.xml" relativeToChangelogFile="true"/>
	<include file="episode/0009_create_episode.xml" relativeToChangelogFile="true"/>
	<include file="movie/0010_create_movie.xml" relativeToChangelogFile="true"/>
	<include file="comic_series/0011_create_comic_series.xml" relativeToChangelogFile="true"/>
	<include file="comics/0012_create_comics.xml" relativeToChangelogFile="true"/>
	<include file="reference/0013_create_reference.xml" relativeToChangelogFile="true"/>
	<include file="comic_strip/0014_create_comic_strip.xml" relativeToChangelogFile="true"/>
	<include file="comic_collection/0015_create_comic_collection.xml" relativeToChangelogFile="true"/>
	<include file="species/0016_create_species.xml" relativeToChangelogFile="true"/>
	<include file="character/0017_create_character_species.xml" relativeToChangelogFile="true"/>
	<include file="organization/0018_create_organization.xml" relativeToChangelogFile="true"/>
	<include file="food/0019_create_food.xml" relativeToChangelogFile="true"/>
	<include file="throttle/0020_create_throttle.xml" relativeToChangelogFile="true"/>
	<include file="location/0021_create_location.xml" relativeToChangelogFile="true"/>
	<include file="book_series/0022_create_book_series.xml" relativeToChangelogFile="true"/>
	<include file="book/0023_create_book.xml" relativeToChangelogFile="true"/>
	<include file="book_collection/0024_create_book_collection.xml" relativeToChangelogFile="true"/>
	<include file="hit/0025_create_endpoint_hit.xml" relativeToChangelogFile="true"/>
	<include file="magazine_series/0026_create_magazine_series.xml" relativeToChangelogFile="true"/>
	<include file="magazine/0027_create_magazine.xml" relativeToChangelogFile="true"/>
	<include file="literature/0028_create_literature.xml" relativeToChangelogFile="true"/>
	<include file="content_rating/0029_create_content_rating.xml" relativeToChangelogFile="true"/>
	<include file="content_language/0030_create_content_language.xml" relativeToChangelogFile="true"/>
	<include file="video_release/0031_create_video_release.xml" relativeToChangelogFile="true"/>
	<include file="country/0032_create_country.xml" relativeToChangelogFile="true"/>
	<include file="trading_card_set/0033_create_trading_card_set.xml" relativeToChangelogFile="true"/>
	<include file="trading_card/0034_create_trading_card.xml" relativeToChangelogFile="true"/>
</databaseChangeLog>
